sasdata/__init__.py
sasdata/_version.py
sasdata/data_util/__init__.py
sasdata/data_util/err1d.py
sasdata/data_util/formatnum.py
sasdata/data_util/loader_exceptions.py
sasdata/data_util/manipulations.py
sasdata/data_util/nxsunit.py
sasdata/data_util/registry.py
sasdata/data_util/uncertainty.py
sasdata/data_util/util.py
sasdata/dataloader/__init__.py
sasdata/dataloader/data_info.py
sasdata/dataloader/filereader.py
sasdata/dataloader/loader.py
sasdata/dataloader/readers/__init__.py
sasdata/dataloader/readers/abs_reader.py
sasdata/dataloader/readers/anton_paar_saxs_reader.py
sasdata/dataloader/readers/ascii_reader.py
sasdata/dataloader/readers/associations.py
sasdata/dataloader/readers/cansas_constants.py
sasdata/dataloader/readers/cansas_reader.py
sasdata/dataloader/readers/cansas_reader_HDF5.py
sasdata/dataloader/readers/csv_reader.py
sasdata/dataloader/readers/danse_reader.py
sasdata/dataloader/readers/red2d_reader.py
sasdata/dataloader/readers/sesans_reader.py
sasdata/dataloader/readers/tiff_reader.py
sasdata/dataloader/readers/xml_reader.py
sasdata/dataloader/readers/schema/cansas1d_invalid_v1_0.xsd
sasdata/dataloader/readers/schema/cansas1d_invalid_v1_1.xsd
sasdata/dataloader/readers/schema/cansas1d_v1_0.xsd
sasdata/dataloader/readers/schema/cansas1d_v1_1.xsd
sasdata/example_data/README.txt
sasdata/example_data/__init__.py
sasdata/example_data/1d_data/10000A_sphere_dsm.xml
sasdata/example_data/1d_data/100nmPinholeSphere.txt
sasdata/example_data/1d_data/100nmSpheresNodQ.txt
sasdata/example_data/1d_data/10wtAOT_Reline_120_reduced.pdh
sasdata/example_data/1d_data/1umSlitSmearSphere.ABS
sasdata/example_data/1d_data/33837rear_1D_1.75_16.5_CanSAS1D.xml
sasdata/example_data/1d_data/33837rear_1D_1.75_16.5_NXcanSAS.h5
sasdata/example_data/1d_data/33837rear_1D_1.75_16.5_NXcanSAS_v3.h5
sasdata/example_data/1d_data/98929.txt
sasdata/example_data/1d_data/AOT_Microemulsion-Core_Contrast.xml
sasdata/example_data/1d_data/AOT_Microemulsion-Drop_Contrast.xml
sasdata-0.11.0.dist-info/METADATA
sasdata-0.11.0.dist-info/WHEEL
sasdata-0.11.0.dist-info/licenses/LICENSE.TXT
sasdata-0.11.0.dist-info/RECORD
