Metadata-Version: 2.4
Name: sasdata
Version: 0.11.0
Summary: Sas Data Loader application
Project-URL: homepage, http://sasview.org
Author-email: SasView Team <developers@sasview.org>
License: BSD-3-Clause
License-File: LICENSE.TXT
Keywords: X-ray,data analysis,neutron,scattering,small-angle
Classifier: Development Status :: 5 - Production/Stable
Classifier: Intended Audience :: Science/Research
Classifier: License :: OSI Approved :: BSD License
Classifier: Programming Language :: Python
Requires-Python: >=3.9
Requires-Dist: h5py
Requires-Dist: lxml
Requires-Dist: numpy
Provides-Extra: test
Requires-Dist: pytest; extra == 'test'
